bitblaster.cp37-win32.pyd
bitblaster-0.0.6.dist-info/LICENSE
bitblaster-0.0.6.dist-info/METADATA
bitblaster-0.0.6.dist-info/WHEEL
bitblaster-0.0.6.dist-info/top_level.txt
bitblaster-0.0.6.dist-info/RECORD
