Metadata-Version: 2.1
Name: bitblaster
Version: 0.0.6
Summary: A test project using pybind11
Home-page: https://github.com/mxklabs/mxklabs-bitblaster2
Author: Mark Kattenbelt
Author-email: mark@mxklabs.co.uk
License: UNKNOWN
Platform: UNKNOWN
Provides-Extra: test
Requires-Dist: pytest ; extra == 'test'
